{
  "users": [
    {
      "id": "0",
      "nombreUsuario": "JD",
      "claveUsuario": "444",
      "tipoUsuario": "admin"
    },
    {
      "id": "7a84",
      "nombreUsuario": "Student",
      "claveUsuario": "001",
      "tipoUsuario": "estudiante",
      "sede": "Desamparados"
    },
    {
      "id": "04c2",
      "nombreUsuario": "Tiburoncin",
      "claveUsuario": "000",
      "tipoUsuario": "estudiante",
      "sede": "Puntarenas"
    }
  ],
  "estadisticas": [
    {
      "id": "b4b9",
      "idEstudiante": "JDiego CorellaCamacho",
      "idCompu": "0000",
      "sede": "San Jose",
      "fechaSalida": "2025-02-27",
      "fechaRegreso": "2025-02-28",
      "estado": false
    },
    {
      "id": "de54",
      "idEstudiante": "Tiburoncin",
      "idCompu": "001",
      "sede": "Puntarenas",
      "fechaSalida": "2025-02-27",
      "fechaRegreso": "2025-02-28",
      "estado": false
    },
    {
      "id": "1b2d",
      "idEstudiante": "Fer",
      "idCompu": "014",
      "sede": "San Jose",
      "fechaSalida": "2025-02-27",
      "fechaRegreso": "2025-02-28",
      "estado": false
    }
  ],
  "formAceptados": [
    {
      "id": "73fb",
      "idEstudiante": "",
      "idCompu": "",
      "sede": "",
      "fechaSalida": "",
      "fechaRegreso": ""
    }
  ],
  "formNegados": []
}